tq_amr/__init__.py
tq_amr/AMR/CodeAnalyzer.py
tq_amr/AMR/__init__.py
tq_amr/AMR/analysis_module_imports.py
tq_amr/graph_dot/Model.py
tq_amr/graph_dot/__init__.py
tq_amr/graph_dot/get_dot_N_png.py
tq_amr/utils/__init__.py
tq_amr-0.0.1.dist-info/METADATA
tq_amr-0.0.1.dist-info/WHEEL
tq_amr-0.0.1.dist-info/top_level.txt
tq_amr-0.0.1.dist-info/RECORD
