Metadata-Version: 2.1
Name: tq_amr
Version: 0.0.1
Summary: Some simple utils.
Home-page: https://gitee.com/torchW/tq_amr.git
Author: TripleQuiz
Author-email: triple_quiz@163.com
License: MIT
Keywords: python,util,analyze module relationship,graph,dot
Classifier: Development Status :: 3 - Alpha
Classifier: License :: OSI Approved :: MIT License
Classifier: Programming Language :: Python :: 3.8
Classifier: Programming Language :: Python :: 3.9
Classifier: Programming Language :: Python :: 3.10
Classifier: Programming Language :: Python :: 3.11
Classifier: Intended Audience :: Developers
Classifier: Operating System :: Microsoft :: Windows
Classifier: Natural Language :: Chinese (Simplified)
Requires-Python: >=3.8, <3.12
Requires-Dist: pydot==3.0.1
Requires-Dist: pygraphviz==1.11
Requires-Dist: tq-utils>=0.1.3.post1
